{
    "fr": {
      "wifi": {
        "titre": "Informations WiFi",
        "networkName": "Nom du réseau : <strong>MonWifi</strong>",
        "password": "Mot de passe : <strong>12345678</strong>"
      },
      "digicode": {
        "title": "Informations Digicodes",
        "entree": "Le code de la boîte à clé se trouve dans le message qui vous a été envoyé sur airbnb et par message."
      }
    },
    "en": {
      "wifi": {
        "title": "WiFi Information",
        "networkName": "Network Name: <strong>MyWifi</strong>",
        "password": "Password: <strong>12345678</strong>"
      },
      "digicode": {
        "title": "Digicode Information",
        "entree": "Access Code: <strong>Check the message you received after booking</strong>"
      }
    }
  }
  